DeepMicroClass/__init__.py
DeepMicroClass/__main__.py
DeepMicroClass/constants.py
DeepMicroClass/model.ckpt
DeepMicroClass/predict.py
DeepMicroClass/train.py
DeepMicroClass/utils.py
DeepMicroClass/demo/test.fa
DeepMicroClass/demo/test.fa_pred_one-hot_hybrid.tsv
DeepMicroClass/model/DeepMicroClass.py
DeepMicroClass/model/SequenceData.py
DeepMicroClass/model/__init__.py
DeepMicroClass-1.0.6.dist-info/LICENSE
DeepMicroClass-1.0.6.dist-info/METADATA
DeepMicroClass-1.0.6.dist-info/WHEEL
DeepMicroClass-1.0.6.dist-info/entry_points.txt
DeepMicroClass-1.0.6.dist-info/top_level.txt
DeepMicroClass-1.0.6.dist-info/RECORD
