Metadata-Version: 2.2
Name: DeepMicroClass
Version: 1.0.6
Summary: DeepMicroClass, a deep learning based contig prediction tool
Home-page: https://github.com/chengsly/DeepMicroClass
Author: Tianqi Tang, Shengwei Hou, Siliangyu Cheng, Jed A. Fuhrman, and Fengzhu Sun
Author-email: tianqit@usc.edu
License: USC-RL v1.0
Platform: any
Classifier: Development Status :: 4 - Beta
Classifier: Intended Audience :: Science/Research
Classifier: License :: Other/Proprietary License
Classifier: Operating System :: OS Independent
Classifier: Programming Language :: Python :: 3 :: Only
Classifier: Programming Language :: Python :: 3.8
Classifier: Programming Language :: Python :: 3.9
Classifier: Programming Language :: Python :: 3.10
Classifier: Programming Language :: Python :: 3.11
Classifier: Topic :: Scientific/Engineering :: Bio-Informatics
Classifier: Topic :: Scientific/Engineering :: Artificial Intelligence
Requires-Python: >=3.8
License-File: LICENSE
Requires-Dist: pandas
Requires-Dist: numpy
Requires-Dist: biopython
Requires-Dist: ete3
Requires-Dist: torch
Requires-Dist: pytorch-lightning
Requires-Dist: torchmetrics
Requires-Dist: tensorboard
Requires-Dist: tqdm
Requires-Dist: scikit-learn
